adc78h89/__init__.py
adc78h89/driver.py
adc78h89/py.typed
adc78h89/tests/__init__.py
adc78h89/tests/test_driver.py
adc78h89-0.0.0.dev5.dist-info/LICENSE
adc78h89-0.0.0.dev5.dist-info/METADATA
adc78h89-0.0.0.dev5.dist-info/WHEEL
adc78h89-0.0.0.dev5.dist-info/top_level.txt
adc78h89-0.0.0.dev5.dist-info/RECORD
