Metadata-Version: 2.1
Name: adc78h89
Version: 0.0.0.dev5
Summary: A Python driver for Texas Instruments ADC78H89 7-Channel, 500 KSPS, 12-Bit A/D Converter
Home-page: https://github.com/blueskysolarracing/adc78h89
Author: Blue Sky Solar Racing
Author-email: blueskysolar@studentorg.utoronto.ca
License: MIT
Project-URL: Documentation, https://adc78h89.readthedocs.io/en/latest/
Project-URL: Source, https://github.com/blueskysolarracing/adc78h89
Project-URL: Tracker, https://github.com/blueskysolarracing/adc78h89/issues
Keywords: python
Classifier: Development Status :: 5 - Production/Stable
Classifier: Intended Audience :: Developers
Classifier: Intended Audience :: Education
Classifier: Topic :: Education
Classifier: Topic :: Scientific/Engineering
Classifier: License :: OSI Approved :: MIT License
Classifier: Operating System :: OS Independent
Classifier: Programming Language :: Python
Classifier: Programming Language :: Python :: 3
Classifier: Programming Language :: Python :: 3 :: Only
Classifier: Programming Language :: Python :: 3.11
Classifier: Programming Language :: Python :: 3.12
Requires-Python: >=3.11
License-File: LICENSE
Requires-Dist: python-periphery <3,>=2.4.1
